fast_ctc_decode-0.3.6.dist-info/METADATA
fast_ctc_decode-0.3.6.dist-info/WHEEL
fast_ctc_decode/__init__.py
fast_ctc_decode/fast_ctc_decode.cpython-310-darwin.so
fast_ctc_decode-0.3.6.dist-info/RECORD
