Metadata-Version: 2.3
Name: fast_ctc_decode
Version: 0.3.6
Author: Vlado Boza <bozavlado@gmail.com>, Chris Seymour <chris.seymour@nanoporetech.com>, Jabari Holder <jholder@and.digital>
Author-email: Vlado Boza <bozavlado@gmail.com>, Chris Seymour <chris.seymour@nanoporetech.com>, Jabari Holder <jholder@and.digital>
